test/__init__.py
test/test_account.py
test/test_events.py
test/test_hooks.py
test/test_images.py
test/test_locations.py
test/test_profiles.py
test/test_scripts.py
test/test_servers.py
test/test_shellusers.py
test/test_snapshots.py
test/test_sshkeys.py
testnewsdkwebdock/__init__.py
testnewsdkwebdock/account.py
testnewsdkwebdock/events.py
testnewsdkwebdock/hooks.py
testnewsdkwebdock/images.py
testnewsdkwebdock/locations.py
testnewsdkwebdock/operation.py
testnewsdkwebdock/profiles.py
testnewsdkwebdock/req.py
testnewsdkwebdock/scripts.py
testnewsdkwebdock/servers.py
testnewsdkwebdock/shellusers.py
testnewsdkwebdock/snapshots.py
testnewsdkwebdock/sshkeys.py
testnewsdkwebdock-2.2.9.dist-info/licenses/LICENCE
testnewsdkwebdock-2.2.9.dist-info/METADATA
testnewsdkwebdock-2.2.9.dist-info/WHEEL
testnewsdkwebdock-2.2.9.dist-info/top_level.txt
testnewsdkwebdock-2.2.9.dist-info/RECORD
