Metadata-Version: 2.4
Name: testnewsdkwebdock
Version: 2.2.9
Summary: Add your description here
Requires-Python: >=3.13
License-File: LICENCE
Requires-Dist: load-dotenv>=0.1.0
Requires-Dist: requests<3,>=2.31.0
Requires-Dist: setuptools>=80.9.0
Dynamic: license-file
